{
  "$schema": "http://schema.management.azure.com/schemas/2015-01-01/deploymentParameters.json#",
  "contentVersion": "1.0.0.0",
  "parameters": {
    "input": {
      "value": {
        "Id": "/providers/Microsoft.Management/managementGroups/ESLZ",
        "Type": "/providers/Microsoft.Management/managementGroups",
        "Name": "ESLZ",
        "TenantId": "4a02ceba-3c5e-478b-8855-a218e02dd6cc",
        "DisplayName": "ESLZ",
        "UpdatedTime": "2020-09-18T00:08:41.1899878Z",
        "UpdatedBy": "b0ae6474-9d4b-4052-ba4e-97cce513ea88",
        "ParentId": "/providers/Microsoft.Management/managementGroups/4a02ceba-3c5e-478b-8855-a218e02dd6cc",
        "ParentName": "4a02ceba-3c5e-478b-8855-a218e02dd6cc",
        "ParentDisplayName": "Tenant Root Group",
        "Children": [
          {
            "Type": "/providers/Microsoft.Management/managementGroups",
            "Id": "/providers/Microsoft.Management/managementGroups/ESLZ-decomissioned",
            "Name": "ESLZ-decomissioned",
            "DisplayName": "ESLZ-decomissioned",
            "Children": null
          },
          {
            "Type": "/providers/Microsoft.Management/managementGroups",
            "Id": "/providers/Microsoft.Management/managementGroups/ESLZ-sandboxes",
            "Name": "ESLZ-sandboxes",
            "DisplayName": "ESLZ-sandboxes",
            "Children": null
          },
          {
            "Type": "/providers/Microsoft.Management/managementGroups",
            "Id": "/providers/Microsoft.Management/managementGroups/ESLZ-landingzones",
            "Name": "ESLZ-landingzones",
            "DisplayName": "ESLZ-landingzones",
            "Children": null
          },
          {
            "Type": "/providers/Microsoft.Management/managementGroups",
            "Id": "/providers/Microsoft.Management/managementGroups/ESLZ-platform",
            "Name": "ESLZ-platform",
            "DisplayName": "ESLZ-platform",
            "Children": null
          }
        ]
      }
    }
  }
}
